{"info": {"abi_version": "2026_0", "arch": "wasm32", "platform": "emscripten_5_0_3", "python": "3.14.0"}, "packages": {"asciitree": {"depends": [], "file_name": "asciitree-0.3.3-py3-none-any.whl", "imports": ["asciitree"], "install_dir": "site", "name": "asciitree", "package_type": "package", "sha256": "391b74388064efea42cbe8f3953513bcc0dd105c2a020c8dcdc8309bfefddc11", "unvendored_tests": false, "version": "0.3.3"}, "attrs": {"depends": ["six"], "file_name": "attrs-26.1.0-py3-none-any.whl", "imports": ["attr", "attrs"], "install_dir": "site", "name": "attrs", "package_type": "package", "sha256": "cfb41b3e7699292a98b81b49c831b0bb1d7d22af509cfd23d16544281a44c8f4", "unvendored_tests": false, "version": "26.1.0"}, "bokeh": {"depends": ["contourpy", "numpy", "jinja2", "pandas", "pillow", "python-dateutil", "six", "typing-extensions", "pyyaml", "xyzservices"], "file_name": "bokeh-3.9.0-py3-none-any.whl", "imports": ["bokeh"], "install_dir": "site", "name": "bokeh", "package_type": "package", "sha256": "39db9a5d9d510963f3c3137e8df881906754a19099be1e8dadfa6d00e1be6a40", "unvendored_tests": false, "version": "3.9.0"}, "click": {"depends": [], "file_name": "click-8.3.1-py3-none-any.whl", "imports": ["click"], "install_dir": "site", "name": "click", "package_type": "package", "sha256": "b1cf700ae0b47bde19461217e30f748157bc18c197ce34de1208d18963cd9bf9", "unvendored_tests": false, "version": "8.3.1"}, "contourpy": {"depends": ["numpy"], "file_name": "contourpy-1.3.3-cp314-cp314-pyemscripten_2026_0_wasm32.whl", "imports": ["contourpy"], "install_dir": "site", "name": "contourpy", "package_type": "package", "sha256": "80e2277edd66e4aa750cffed82d5fa604bda4b3e4922d61611d03cf370841063", "unvendored_tests": false, "version": "1.3.3"}, "cycler": {"depends": ["six"], "file_name": "cycler-0.12.1-py3-none-any.whl", "imports": ["cycler"], "install_dir": "site", "name": "cycler", "package_type": "package", "sha256": "29fb7f84858c4b2826f7cfc47a01db72a1d2da44cac15b0d6ac141d00fec1ea0", "unvendored_tests": false, "version": "0.12.1"}, "demes": {"depends": ["attrs", "ruamel.yaml"], "file_name": "demes-0.2.3-py3-none-any.whl", "imports": ["demes"], "install_dir": "site", "name": "demes", "package_type": "package", "sha256": "e5980d73643516f297b2d8b21339fc92f3e9af784d8c4ae5c196fd93b913f836", "unvendored_tests": false, "version": "0.2.3"}, "deprecated": {"depends": ["wrapt"], "file_name": "deprecated-1.3.1-py2.py3-none-any.whl", "imports": ["deprecated"], "install_dir": "site", "name": "deprecated", "package_type": "package", "sha256": "9c070fa30ba8fb8aae683d846efdf9ed0c0e8d0db679ccebd90bb734024c93f9", "unvendored_tests": false, "version": "1.3.1"}, "fonttools": {"depends": [], "file_name": "fonttools-4.62.1-py3-none-any.whl", "imports": ["fontTools"], "install_dir": "site", "name": "fonttools", "package_type": "package", "sha256": "2448e64db82115224868460d01dc234bb1e17f2f061940dcfcbb97711b5ee419", "unvendored_tests": false, "version": "4.62.1"}, "humanize": {"depends": [], "file_name": "humanize-4.15.0-py3-none-any.whl", "imports": ["humanize"], "install_dir": "site", "name": "humanize", "package_type": "package", "sha256": "57acac7ae95c825529f52bc017b67847c205f623c37cc40fa585a4c0a04094e7", "unvendored_tests": false, "version": "4.15.0"}, "jinja2": {"depends": ["markupsafe"], "file_name": "jinja2-3.1.6-py3-none-any.whl", "imports": ["jinja2"], "install_dir": "site", "name": "Jinja2", "package_type": "package", "sha256": "68627b2704828a882ba1f9c550c192e90abf2c35f80221dc9f4c2b1fa5e2d817", "unvendored_tests": false, "version": "3.1.6"}, "jsonschema": {"depends": ["attrs", "pyrsistent", "referencing", "jsonschema_specifications"], "file_name": "jsonschema-4.26.0-py3-none-any.whl", "imports": ["jsonschema"], "install_dir": "site", "name": "jsonschema", "package_type": "package", "sha256": "1bf736484812f2d7797e2b22ff7779c665299d93df083f8eb96a1606568d6cb6", "unvendored_tests": true, "version": "4.26.0"}, "jsonschema-specifications": {"depends": ["referencing"], "file_name": "jsonschema_specifications-2025.9.1-py3-none-any.whl", "imports": ["jsonschema_specifications"], "install_dir": "site", "name": "jsonschema_specifications", "package_type": "package", "sha256": "72e2ca15211167b6ec7155f238a360c4fcdc16ab8ef1c795822096ecd5a201c5", "unvendored_tests": true, "version": "2025.9.1"}, "jsonschema-specifications-tests": {"depends": ["jsonschema_specifications"], "file_name": "jsonschema-specifications-tests.tar", "imports": [], "install_dir": "site", "name": "jsonschema_specifications-tests", "package_type": "package", "sha256": "c294722289d71aa6c13ac15dbe719420e64dffef15a548c98542eae4d75c6180", "unvendored_tests": false, "version": "2025.9.1"}, "jsonschema-tests": {"depends": ["jsonschema"], "file_name": "jsonschema-tests.tar", "imports": [], "install_dir": "site", "name": "jsonschema-tests", "package_type": "package", "sha256": "6e0eef26fc47834011c0edd0d1ec743238fe4d12361a80907992270cc86a588f", "unvendored_tests": false, "version": "4.26.0"}, "kiwisolver": {"depends": [], "file_name": "kiwisolver-1.5.0-cp314-cp314-pyemscripten_2026_0_wasm32.whl", "imports": ["kiwisolver"], "install_dir": "site", "name": "kiwisolver", "package_type": "package", "sha256": "11d5a4caa5ced092d1139a47c6593e24b788c2a7615ba0d546308ee9871468ee", "unvendored_tests": false, "version": "1.5.0"}, "libopenblas": {"depends": [], "file_name": "libopenblas-0.3.28.zip", "imports": [], "install_dir": "dynlib", "name": "libopenblas", "package_type": "shared_library", "sha256": "b5a63ae754e9a00bcca27a84af0d8cbee97e24452dd372998c10e77fe22468cb", "unvendored_tests": false, "version": "0.3.28"}, "markupsafe": {"depends": [], "file_name": "markupsafe-3.0.3-cp314-cp314-pyemscripten_2026_0_wasm32.whl", "imports": ["markupsafe"], "install_dir": "site", "name": "MarkupSafe", "package_type": "package", "sha256": "c10f122d0819afeb6207736ba86bfcd487dcbddde4282e3b527ae5cd99434209", "unvendored_tests": false, "version": "3.0.3"}, "matplotlib": {"depends": ["contourpy", "cycler", "fonttools", "kiwisolver", "numpy", "packaging", "pillow", "pyparsing", "python-dateutil", "pytz"], "file_name": "matplotlib-3.10.8-cp314-cp314-pyemscripten_2026_0_wasm32.whl", "imports": ["pylab", "mpl_toolkits", "matplotlib"], "install_dir": "site", "name": "matplotlib", "package_type": "package", "sha256": "16fcb9ba3ee13d0ffc9f1f35a08396139c7fd70d754b1a1047cae42f398b45e4", "unvendored_tests": true, "version": "3.10.8"}, "matplotlib-tests": {"depends": ["matplotlib"], "file_name": "matplotlib-tests.tar", "imports": [], "install_dir": "site", "name": "matplotlib-tests", "package_type": "package", "sha256": "5e0031dab1b1a4f19e2f4f03f4edc3801285f3e88ca7d15a0223f874510cd978", "unvendored_tests": false, "version": "3.10.8"}, "micropip": {"depends": [], "file_name": "micropip-0.11.1-py3-none-any.whl", "imports": ["micropip"], "install_dir": "site", "name": "micropip", "package_type": "package", "sha256": "31c75a8621f88494deab40bfef7ca25c15605420f4bfec8f9c68b16cac6ba5bd", "unvendored_tests": false, "version": "0.11.1"}, "msprime": {"depends": ["numpy", "newick", "tskit", "demes", "rpds-py"], "file_name": "msprime-1.4.1-cp314-cp314-pyemscripten_2026_0_wasm32.whl", "imports": ["msprime"], "install_dir": "site", "name": "msprime", "package_type": "package", "sha256": "1bf1d3ab0ecd545adc45ddb9c2b6f0717ce68f1dbcd7f2bb0fe456361b5a1d7a", "unvendored_tests": false, "version": "1.4.1"}, "newick": {"depends": [], "file_name": "newick-1.11.0-py2.py3-none-any.whl", "imports": ["newick"], "install_dir": "site", "name": "newick", "package_type": "package", "sha256": "f9fc3bd08fa9cf88f6d55e43a41a8e62195457d47d16624917fc90d63e5dbe3a", "unvendored_tests": false, "version": "1.11.0"}, "numcodecs": {"depends": ["deprecated", "numpy"], "file_name": "numcodecs-0.15.1-cp314-cp314-pyemscripten_2026_0_wasm32.whl", "imports": ["numcodecs"], "install_dir": "site", "name": "numcodecs", "package_type": "package", "sha256": "73dbd61553e0057a3ee2af2a3296d39e69377ddd7f174b26f1d1d92dfda3b8de", "unvendored_tests": true, "version": "0.15.1"}, "numcodecs-tests": {"depends": ["numcodecs"], "file_name": "numcodecs-tests.tar", "imports": [], "install_dir": "site", "name": "numcodecs-tests", "package_type": "package", "sha256": "4b79bfc22ed27b3833541c6d79b4e58481fd03dc929e27739dea8fa60dac725c", "unvendored_tests": false, "version": "0.15.1"}, "numpy": {"depends": [], "file_name": "numpy-2.4.3-cp314-cp314-pyemscripten_2026_0_wasm32.whl", "imports": ["numpy"], "install_dir": "site", "name": "numpy", "package_type": "package", "sha256": "d398e268ea02a84680ca890c261ef7ecc384421fd10600d671fee2993014ee7e", "unvendored_tests": false, "version": "2.4.3"}, "packaging": {"depends": [], "file_name": "packaging-26.1-py3-none-any.whl", "imports": ["packaging"], "install_dir": "site", "name": "packaging", "package_type": "package", "sha256": "778e877a5bc17b9ed9270215978c4652d0beefe048da21ca14c829ac7ce4eba8", "unvendored_tests": false, "version": "26.1"}, "pandas": {"depends": ["numpy", "python-dateutil", "pytz"], "file_name": "pandas-3.0.2-cp314-cp314-pyemscripten_2026_0_wasm32.whl", "imports": ["pandas"], "install_dir": "site", "name": "pandas", "package_type": "package", "sha256": "9fd65867c381184e35a0a57fdc67843afb61511c206f8160f73042270a34e8b2", "unvendored_tests": true, "version": "3.0.2"}, "pandas-tests": {"depends": ["pandas"], "file_name": "pandas-tests.tar", "imports": [], "install_dir": "site", "name": "pandas-tests", "package_type": "package", "sha256": "0121e8392b24bcce85ec79b771bf79b0be5628ac6fc270e1a460a6c6e61e7f5a", "unvendored_tests": false, "version": "3.0.2"}, "pillow": {"depends": [], "file_name": "pillow-12.2.0-cp314-cp314-pyemscripten_2026_0_wasm32.whl", "imports": ["PIL"], "install_dir": "site", "name": "Pillow", "package_type": "package", "sha256": "b46a6c94ad3c56cb62c84e3e133290e8e52773d34e4fbb2855715ee1ceab8d4c", "unvendored_tests": false, "version": "12.2.0"}, "pydoc-data": {"depends": [], "file_name": "pydoc_data-1.0.0-py2.py3-none-any.whl", "imports": ["pydoc_data"], "install_dir": "site", "name": "pydoc_data", "package_type": "package", "sha256": "c92018a34ad961b5275ce71c70f7a984c3eeccd8db2b5fa1dc3ced943cb024be", "unvendored_tests": false, "version": "1.0.0"}, "pyodide-http": {"depends": [], "file_name": "pyodide_http-0.2.2-py3-none-any.whl", "imports": ["pyodide_http"], "install_dir": "site", "name": "pyodide-http", "package_type": "package", "sha256": "7ced3c594decbe4f676708f8fcb5a04fd151d1c5d1550217a21b4467642133ea", "unvendored_tests": false, "version": "0.2.2"}, "pyodide-unix-timezones": {"depends": [], "file_name": "pyodide_unix_timezones-1.0.0-py3-none-any.whl", "imports": ["unix_timezones"], "install_dir": "site", "name": "pyodide-unix-timezones", "package_type": "package", "sha256": "3be244c2334cf64be00f6b9292a439642ba3434e083210083d473ddf152648a1", "unvendored_tests": false, "version": "1.0.0"}, "pyparsing": {"depends": [], "file_name": "pyparsing-3.3.2-py3-none-any.whl", "imports": ["pyparsing"], "install_dir": "site", "name": "pyparsing", "package_type": "package", "sha256": "54591674204764c5a3a9c254cdc2ffb5488e6fab238b58f35cb160636378db4f", "unvendored_tests": false, "version": "3.3.2"}, "pyrsistent": {"depends": [], "file_name": "pyrsistent-0.20.0-cp314-cp314-pyemscripten_2026_0_wasm32.whl", "imports": ["_pyrsistent_version", "pyrsistent"], "install_dir": "site", "name": "pyrsistent", "package_type": "package", "sha256": "feb16c32f36cb72953df7be41f7ab874461c4b50980560a2c0611c3f661b219b", "unvendored_tests": false, "version": "0.20.0"}, "pysam": {"depends": [], "file_name": "pysam-0.23.0-cp314-cp314-pyemscripten_2026_0_wasm32.whl", "imports": ["pysam"], "install_dir": "site", "name": "pysam", "package_type": "package", "sha256": "a2e7023feab8e62eb3d94d77b317a79d88455491a9dfd2b667f8f6fd9a49112a", "unvendored_tests": false, "version": "0.23.0"}, "python-dateutil": {"depends": ["six"], "file_name": "python_dateutil-2.9.0.post0-py2.py3-none-any.whl", "imports": ["dateutil"], "install_dir": "site", "name": "python-dateutil", "package_type": "package", "sha256": "22979a5d3b8b5abc6c5300cbb77f3d5a88acfe3de4431d065e97b3e18052cba8", "unvendored_tests": false, "version": "2.9.0.post0"}, "pytz": {"depends": [], "file_name": "pytz-2026.1.post1-py2.py3-none-any.whl", "imports": ["pytz"], "install_dir": "site", "name": "pytz", "package_type": "package", "sha256": "21480d46bb5cb2e50e9ab3d525838974880f2320dce7c69ed5247d29334ca832", "unvendored_tests": false, "version": "2026.1.post1"}, "pyyaml": {"depends": [], "file_name": "pyyaml-6.0.3-cp314-cp314-pyemscripten_2026_0_wasm32.whl", "imports": ["_yaml", "yaml"], "install_dir": "site", "name": "pyyaml", "package_type": "package", "sha256": "a516af90a3dde1541b5e2f1c186fc0db38ac61f52217fbcdf6618648afd0e622", "unvendored_tests": false, "version": "6.0.3"}, "referencing": {"depends": ["attrs", "rpds-py", "typing-extensions"], "file_name": "referencing-0.37.0-py3-none-any.whl", "imports": ["referencing"], "install_dir": "site", "name": "referencing", "package_type": "package", "sha256": "113591fdf7c76cc8c93e959c977e09528ee6e279711b8ee85ab7d46e9a46a6aa", "unvendored_tests": true, "version": "0.37.0"}, "referencing-tests": {"depends": ["referencing"], "file_name": "referencing-tests.tar", "imports": [], "install_dir": "site", "name": "referencing-tests", "package_type": "package", "sha256": "796a0c0c4a7596e6e8dc3cd9c18458761e5c0df1934232b05383dee458dcd160", "unvendored_tests": false, "version": "0.37.0"}, "rpds-py": {"depends": [], "file_name": "rpds_py-0.30.0-cp314-cp314-pyemscripten_2026_0_wasm32.whl", "imports": ["rpds"], "install_dir": "site", "name": "rpds-py", "package_type": "package", "sha256": "a2ecbe0d93e9951c76e449670b43248cb68f3c315609544a308fed6e236ed775", "unvendored_tests": false, "version": "0.30.0"}, "ruamel-yaml": {"depends": [], "file_name": "ruamel_yaml-0.19.1-py3-none-any.whl", "imports": ["ruamel"], "install_dir": "site", "name": "ruamel.yaml", "package_type": "package", "sha256": "b7e6cfdf6b053e26a32c1dae615f64a38777116f80565d9e1b78cee194b04299", "unvendored_tests": false, "version": "0.19.1"}, "sc2ts": {"depends": ["tskit", "tszip", "pandas", "tqdm", "zarr", "click", "tomli", "humanize"], "file_name": "sc2ts-1.0.2-py3-none-any.whl", "imports": ["sc2ts"], "install_dir": "site", "name": "sc2ts", "package_type": "package", "sha256": "ba9abde525affc7e5f73eed474c4ea9d3230fe2c04f9c346a0801223e79c6c15", "unvendored_tests": false, "version": "1.0.2"}, "scipy": {"depends": ["numpy"], "file_name": "scipy-1.17.1-cp314-cp314-pyemscripten_2026_0_wasm32.whl", "imports": ["scipy"], "install_dir": "site", "name": "scipy", "package_type": "package", "sha256": "62e5b508c21a6e5e458d97c78e9e99a435b157efe3c8d08760efd8c6b30cf84e", "unvendored_tests": true, "version": "1.17.1"}, "scipy-tests": {"depends": ["scipy"], "file_name": "scipy-tests.tar", "imports": [], "install_dir": "site", "name": "scipy-tests", "package_type": "package", "sha256": "b59da94b737a9f8d3c42ed2a3916a1ae6e7e86cc4a2289adf6c114a60c5b99d3", "unvendored_tests": false, "version": "1.17.1"}, "six": {"depends": [], "file_name": "six-1.17.0-py2.py3-none-any.whl", "imports": ["six"], "install_dir": "site", "name": "six", "package_type": "package", "sha256": "57dd756bf69e8a9f3cb0ebb4cce229c3f24fdf29f325fb71ebca504a199216fb", "unvendored_tests": false, "version": "1.17.0"}, "tblib": {"depends": [], "file_name": "tblib-3.2.2-py3-none-any.whl", "imports": ["tblib"], "install_dir": "site", "name": "tblib", "package_type": "package", "sha256": "32b2036b6db2047a6fad32637eaa4712cf042c28507c3de6780efcfa932c37c3", "unvendored_tests": false, "version": "3.2.2"}, "tomli": {"depends": [], "file_name": "tomli-2.4.1-py3-none-any.whl", "imports": ["tomli"], "install_dir": "site", "name": "tomli", "package_type": "package", "sha256": "1431805055569db77728eb0a713a8d32c0ad7b07553af7436ba3387d4fa64530", "unvendored_tests": false, "version": "2.4.1"}, "tqdm": {"depends": [], "file_name": "tqdm-4.67.3-py3-none-any.whl", "imports": ["tqdm"], "install_dir": "site", "name": "tqdm", "package_type": "package", "sha256": "bda54ad4be9306bbecc25c4c60506bee31043b1932c137877291e68a17f43462", "unvendored_tests": false, "version": "4.67.3"}, "tskit": {"depends": ["numpy", "jsonschema", "rpds-py"], "file_name": "tskit-1.0.2-cp314-cp314-pyemscripten_2026_0_wasm32.whl", "imports": ["tskit"], "install_dir": "site", "name": "tskit", "package_type": "package", "sha256": "12a3d107840c9840ef5c53d0a6afda027d41d87efceb44179bde5fa08ec2f067", "unvendored_tests": false, "version": "1.0.2"}, "tszip": {"depends": ["numpy", "humanize", "tskit", "zarr"], "file_name": "tszip-0.3.1-py3-none-any.whl", "imports": ["tszip"], "install_dir": "site", "name": "tszip", "package_type": "package", "sha256": "7328bef30e1b5e2de06d9306c444edc606b8e83c6ccef32e2946230361eb629f", "unvendored_tests": false, "version": "0.3.1"}, "typing-extensions": {"depends": [], "file_name": "typing_extensions-4.15.0-py3-none-any.whl", "imports": ["typing_extensions"], "install_dir": "site", "name": "typing-extensions", "package_type": "package", "sha256": "0faa9a07e3a876685af0aa419b17f3d11a1ebb7389b7cc64efc0a0bff8285693", "unvendored_tests": false, "version": "4.15.0"}, "wrapt": {"depends": [], "file_name": "wrapt-2.1.2-cp314-cp314-pyemscripten_2026_0_wasm32.whl", "imports": ["wrapt"], "install_dir": "site", "name": "wrapt", "package_type": "package", "sha256": "05c78c6ed975992208cf27d547b111dd9603fe9ea3a5243b9ee0f1651885daeb", "unvendored_tests": false, "version": "2.1.2"}, "xyzservices": {"depends": [], "file_name": "xyzservices-2026.3.0-py3-none-any.whl", "imports": ["xyzservices"], "install_dir": "site", "name": "xyzservices", "package_type": "package", "sha256": "2440e0a5e9b7e07473bfd7a5839ed2973434b943b203c310238322ee62d757ec", "unvendored_tests": true, "version": "2026.3.0"}, "xyzservices-tests": {"depends": ["xyzservices"], "file_name": "xyzservices-tests.tar", "imports": [], "install_dir": "site", "name": "xyzservices-tests", "package_type": "package", "sha256": "c9212f4c0ecacc1e0f3693b8ed8df9466adb1e3d178e716a6a2d54360855b57e", "unvendored_tests": false, "version": "2026.3.0"}, "zarr": {"depends": ["numpy", "asciitree", "numcodecs"], "file_name": "zarr-2.18.7-py3-none-any.whl", "imports": ["zarr"], "install_dir": "site", "name": "zarr", "package_type": "package", "sha256": "12221f6d33ed67fb1510d8edcbf68abc2da10813fbf0854c4fc160fa51187323", "unvendored_tests": true, "version": "2.18.7"}, "zarr-tests": {"depends": ["zarr"], "file_name": "zarr-tests.tar", "imports": [], "install_dir": "site", "name": "zarr-tests", "package_type": "package", "sha256": "f7f050b597801fc2c9d5078e8e5ec18bdc73ca8bff8fbfc64dd64c41c38d9250", "unvendored_tests": false, "version": "2.18.7"}}}